<annotation>
	<folder>B</folder>
	<filename>B1007.jpg</filename>
	<path>/home/biankatpas/workspace/tcc/dataset/asl_alphabet_train/B/B1007.jpg</path>
	<source>
		<database>Unknown</database>
	</source>
	<size>
		<width>200</width>
		<height>200</height>
		<depth>3</depth>
	</size>
	<segmented>0</segmented>
	<object>
		<name>b</name>
		<pose>Unspecified</pose>
		<truncated>0</truncated>
		<difficult>0</difficult>
		<bndbox>
			<xmin>55</xmin>
			<ymin>35</ymin>
			<xmax>138</xmax>
			<ymax>197</ymax>
		</bndbox>
	</object>
</annotation>
